dualstudent/__init__.py
dualstudent/datasets/__init__.py
dualstudent/datasets/timit.py
dualstudent/io/__init__.py
dualstudent/io/_sphere.py
dualstudent/io/_transcription.py
dualstudent/metrics/__init__.py
dualstudent/metrics/_per.py
dualstudent/metrics/_utils.py
dualstudent/models/__init__.py
dualstudent/models/_dual_student.py
dualstudent/models/_utils.py
dualstudent/preprocess/__init__.py
dualstudent/preprocess/_speech.py
dualstudent/preprocess/_utils.py
dualstudent_asr-0.1.2.dist-info/LICENSE
dualstudent_asr-0.1.2.dist-info/METADATA
dualstudent_asr-0.1.2.dist-info/WHEEL
dualstudent_asr-0.1.2.dist-info/top_level.txt
dualstudent_asr-0.1.2.dist-info/RECORD
