Metadata-Version: 2.1
Name: dualstudent-asr
Version: 0.1.2
Summary: Dual Student for Automatic Speech Recognition
Home-page: https://github.com/franco-ruggeri/dt2119-dualstudent-asr
Author: Franco Ruggeri, Andrea Caraffa, Kevin Dalla Torre Castillo, Simone Porcu
Author-email: fruggeri@kth.se, caraffa@kth.se, kevindt@kth.se, porcu@kth.se
License: GPL
Platform: UNKNOWN
